[
  {
    "match_id": "9201",
    "season": 2006,
    "player_key": "寺川 能人",
    "player_name": "寺川 能人",
    "time": "65'",
    "minute": 65,
    "is_own_goal": false
  },
  {
    "match_id": "9201",
    "season": 2006,
    "player_key": "エジミウソン",
    "player_name": "エジミウソン",
    "time": "76'",
    "minute": 76,
    "is_own_goal": false
  },
  {
    "match_id": "9211",
    "season": 2006,
    "player_key": "エジミウソン",
    "player_name": "エジミウソン",
    "time": "18'",
    "minute": 18,
    "is_own_goal": false
  },
  {
    "match_id": "9211",
    "season": 2006,
    "player_key": "エジミウソン",
    "player_name": "エジミウソン",
    "time": "75'",
    "minute": 75,
    "is_own_goal": false
  },
  {
    "match_id": "9228",
    "season": 2006,
    "player_key": "エジミウソン",
    "player_name": "エジミウソン",
    "time": "52'",
    "minute": 52,
    "is_own_goal": false
  },
  {
    "match_id": "9143",
    "season": 2006,
    "player_key": "田中 亜土夢",
    "player_name": "田中 亜土夢",
    "time": "24'",
    "minute": 24,
    "is_own_goal": false
  },
  {
    "match_id": "9143",
    "season": 2006,
    "player_key": "エジミウソン",
    "player_name": "エジミウソン",
    "time": "31'",
    "minute": 31,
    "is_own_goal": false
  },
  {
    "match_id": "9143",
    "season": 2006,
    "player_key": "エジミウソン",
    "player_name": "エジミウソン",
    "time": "89'",
    "minute": 89,
    "is_own_goal": false
  },
  {
    "match_id": "9241",
    "season": 2006,
    "player_key": "中原 貴之",
    "player_name": "中原 貴之",
    "time": "81'",
    "minute": 81,
    "is_own_goal": false
  },
  {
    "match_id": "9244",
    "season": 2006,
    "player_key": "矢野 貴章",
    "player_name": "矢野 貴章",
    "time": "46'",
    "minute": 46,
    "is_own_goal": false
  },
  {
    "match_id": "9244",
    "season": 2006,
    "player_key": "鈴木 慎吾",
    "player_name": "鈴木 慎吾",
    "time": "63'",
    "minute": 63,
    "is_own_goal": false
  },
  {
    "match_id": "9244",
    "season": 2006,
    "player_key": "田中 亜土夢",
    "player_name": "田中 亜土夢",
    "time": "69'",
    "minute": 69,
    "is_own_goal": false
  },
  {
    "match_id": "9244",
    "season": 2006,
    "player_key": "河原 和寿",
    "player_name": "河原 和寿",
    "time": "89'",
    "minute": 89,
    "is_own_goal": false
  },
  {
    "match_id": "9144",
    "season": 2006,
    "player_key": "鈴木 慎吾",
    "player_name": "鈴木 慎吾",
    "time": "20'",
    "minute": 20,
    "is_own_goal": false
  },
  {
    "match_id": "9144",
    "season": 2006,
    "player_key": "岡山 哲也",
    "player_name": "岡山 哲也",
    "time": "63'",
    "minute": 63,
    "is_own_goal": false
  },
  {
    "match_id": "9257",
    "season": 2006,
    "player_key": "鈴木 慎吾",
    "player_name": "鈴木 慎吾",
    "time": "27'",
    "minute": 27,
    "is_own_goal": false
  },
  {
    "match_id": "9257",
    "season": 2006,
    "player_key": "海本 慶治",
    "player_name": "海本 慶治",
    "time": "83'",
    "minute": 83,
    "is_own_goal": false
  },
  {
    "match_id": "9146",
    "season": 2006,
    "player_key": "矢野 貴章",
    "player_name": "矢野 貴章",
    "time": "38'",
    "minute": 38,
    "is_own_goal": false
  },
  {
    "match_id": "9146",
    "season": 2006,
    "player_key": "中原 貴之",
    "player_name": "中原 貴之",
    "time": "52'",
    "minute": 52,
    "is_own_goal": false
  },
  {
    "match_id": "9279",
    "season": 2006,
    "player_key": "中原 貴之",
    "player_name": "中原 貴之",
    "time": "43'",
    "minute": 43,
    "is_own_goal": false
  },
  {
    "match_id": "9283",
    "season": 2006,
    "player_key": "シルビーニョ",
    "player_name": "シルビーニョ",
    "time": "81'",
    "minute": 81,
    "is_own_goal": false
  },
  {
    "match_id": "9294",
    "season": 2006,
    "player_key": "三田 光",
    "player_name": "三田 光",
    "time": "42'",
    "minute": 42,
    "is_own_goal": false
  },
  {
    "match_id": "9294",
    "season": 2006,
    "player_key": "鈴木 慎吾",
    "player_name": "鈴木 慎吾",
    "time": "56'",
    "minute": 56,
    "is_own_goal": false
  },
  {
    "match_id": "9294",
    "season": 2006,
    "player_key": "鈴木 慎吾",
    "player_name": "鈴木 慎吾",
    "time": "71'",
    "minute": 71,
    "is_own_goal": false
  },
  {
    "match_id": "9294",
    "season": 2006,
    "player_key": "ファビーニョ",
    "player_name": "ファビーニョ",
    "time": "78'",
    "minute": 78,
    "is_own_goal": false
  },
  {
    "match_id": "9302",
    "season": 2006,
    "player_key": "エジミウソン",
    "player_name": "エジミウソン",
    "time": "12'",
    "minute": 12,
    "is_own_goal": false
  },
  {
    "match_id": "9302",
    "season": 2006,
    "player_key": "シルビーニョ",
    "player_name": "シルビーニョ",
    "time": "70'",
    "minute": 70,
    "is_own_goal": false
  },
  {
    "match_id": "9337",
    "season": 2006,
    "player_key": "矢野 貴章",
    "player_name": "矢野 貴章",
    "time": "10'",
    "minute": 10,
    "is_own_goal": false
  },
  {
    "match_id": "9345",
    "season": 2006,
    "player_key": "鈴木 慎吾",
    "player_name": "鈴木 慎吾",
    "time": "27'",
    "minute": 27,
    "is_own_goal": false
  },
  {
    "match_id": "9345",
    "season": 2006,
    "player_key": "鈴木 慎吾",
    "player_name": "鈴木 慎吾",
    "time": "44'",
    "minute": 44,
    "is_own_goal": false
  },
  {
    "match_id": "9352",
    "season": 2006,
    "player_key": "エジミウソン",
    "player_name": "エジミウソン",
    "time": "06'",
    "minute": 6,
    "is_own_goal": false
  },
  {
    "match_id": "9364",
    "season": 2006,
    "player_key": "ファビーニョ",
    "player_name": "ファビーニョ",
    "time": "00'",
    "minute": 0,
    "is_own_goal": false
  },
  {
    "match_id": "9364",
    "season": 2006,
    "player_key": "松下 年宏",
    "player_name": "松下 年宏",
    "time": "07'",
    "minute": 7,
    "is_own_goal": false
  },
  {
    "match_id": "9364",
    "season": 2006,
    "player_key": "鈴木 慎吾",
    "player_name": "鈴木 慎吾",
    "time": "76'",
    "minute": 76,
    "is_own_goal": false
  },
  {
    "match_id": "9392",
    "season": 2006,
    "player_key": null,
    "player_name": "オウンゴール",
    "time": "36'",
    "minute": 36,
    "is_own_goal": true
  },
  {
    "match_id": "9405",
    "season": 2006,
    "player_key": "エジミウソン",
    "player_name": "エジミウソン",
    "time": "09'",
    "minute": 9,
    "is_own_goal": false
  },
  {
    "match_id": "9405",
    "season": 2006,
    "player_key": "鈴木 慎吾",
    "player_name": "鈴木 慎吾",
    "time": "58'",
    "minute": 58,
    "is_own_goal": false
  },
  {
    "match_id": "9405",
    "season": 2006,
    "player_key": "エジミウソン",
    "player_name": "エジミウソン",
    "time": "72'",
    "minute": 72,
    "is_own_goal": false
  },
  {
    "match_id": "9406",
    "season": 2006,
    "player_key": "鈴木 慎吾",
    "player_name": "鈴木 慎吾",
    "time": "12'",
    "minute": 12,
    "is_own_goal": false
  },
  {
    "match_id": "9406",
    "season": 2006,
    "player_key": "松下 年宏",
    "player_name": "松下 年宏",
    "time": "17'",
    "minute": 17,
    "is_own_goal": false
  },
  {
    "match_id": "9406",
    "season": 2006,
    "player_key": "松下 年宏",
    "player_name": "松下 年宏",
    "time": "74'",
    "minute": 74,
    "is_own_goal": false
  },
  {
    "match_id": "9406",
    "season": 2006,
    "player_key": "エジミウソン",
    "player_name": "エジミウソン",
    "time": "83'",
    "minute": 83,
    "is_own_goal": false
  },
  {
    "match_id": "9419",
    "season": 2006,
    "player_key": null,
    "player_name": "オウンゴール",
    "time": "75'",
    "minute": 75,
    "is_own_goal": true
  },
  {
    "match_id": "9426",
    "season": 2006,
    "player_key": "内田 潤",
    "player_name": "内田 潤",
    "time": "49'",
    "minute": 49,
    "is_own_goal": false
  },
  {
    "match_id": "9437",
    "season": 2006,
    "player_key": "矢野 貴章",
    "player_name": "矢野 貴章",
    "time": "28'",
    "minute": 28,
    "is_own_goal": false
  },
  {
    "match_id": "9453",
    "season": 2006,
    "player_key": "シルビーニョ",
    "player_name": "シルビーニョ",
    "time": "08'",
    "minute": 8,
    "is_own_goal": false
  },
  {
    "match_id": "9453",
    "season": 2006,
    "player_key": "エジミウソン",
    "player_name": "エジミウソン",
    "time": "31'",
    "minute": 31,
    "is_own_goal": false
  },
  {
    "match_id": "9453",
    "season": 2006,
    "player_key": "矢野 貴章",
    "player_name": "矢野 貴章",
    "time": "58'",
    "minute": 58,
    "is_own_goal": false
  },
  {
    "match_id": "9467",
    "season": 2006,
    "player_key": "矢野 貴章",
    "player_name": "矢野 貴章",
    "time": "39'",
    "minute": 39,
    "is_own_goal": false
  },
  {
    "match_id": "9467",
    "season": 2006,
    "player_key": "ファビーニョ",
    "player_name": "ファビーニョ",
    "time": "69'",
    "minute": 69,
    "is_own_goal": false
  },
  {
    "match_id": "9469",
    "season": 2006,
    "player_key": "本間 勲",
    "player_name": "本間 勲",
    "time": "45'",
    "minute": 45,
    "is_own_goal": false
  },
  {
    "match_id": "9486",
    "season": 2006,
    "player_key": "矢野 貴章",
    "player_name": "矢野 貴章",
    "time": "64'",
    "minute": 64,
    "is_own_goal": false
  },
  {
    "match_id": "9490",
    "season": 2006,
    "player_key": "ファビーニョ",
    "player_name": "ファビーニョ",
    "time": "89'",
    "minute": 89,
    "is_own_goal": false
  }
]