[
  {
    "match_id": "15982",
    "season": 2014,
    "player_key": "巻 誠一郎",
    "player_name": "巻 誠一郎",
    "type": "警告",
    "time": "64'",
    "minute": 64
  },
  {
    "match_id": "15982",
    "season": 2014,
    "player_key": "齊藤 和樹",
    "player_name": "齊藤 和樹",
    "type": "警告",
    "time": "73'",
    "minute": 73
  },
  {
    "match_id": "15994",
    "season": 2014,
    "player_key": "橋本 拳人",
    "player_name": "橋本 拳人",
    "type": "警告",
    "time": "31'",
    "minute": 31
  },
  {
    "match_id": "15994",
    "season": 2014,
    "player_key": "仲間 隼斗",
    "player_name": "仲間 隼斗",
    "type": "警告",
    "time": "42'",
    "minute": 42
  },
  {
    "match_id": "15994",
    "season": 2014,
    "player_key": "片山 奨典",
    "player_name": "片山 奨典",
    "type": "警告",
    "time": "68'",
    "minute": 68
  },
  {
    "match_id": "16005",
    "season": 2014,
    "player_key": "齊藤 和樹",
    "player_name": "齊藤 和樹",
    "type": "警告",
    "time": "29'",
    "minute": 29
  },
  {
    "match_id": "16005",
    "season": 2014,
    "player_key": "園田 拓也",
    "player_name": "園田 拓也",
    "type": "警告",
    "time": "51'",
    "minute": 51
  },
  {
    "match_id": "16026",
    "season": 2014,
    "player_key": "仲間 隼斗",
    "player_name": "仲間 隼斗",
    "type": "警告",
    "time": "55'",
    "minute": 55
  },
  {
    "match_id": "16026",
    "season": 2014,
    "player_key": "中山 雄登",
    "player_name": "中山 雄登",
    "type": "警告",
    "time": "90'+4",
    "minute": 94
  },
  {
    "match_id": "16038",
    "season": 2014,
    "player_key": "篠原 弘次郎",
    "player_name": "篠原 弘次郎",
    "type": "警告",
    "time": "31'",
    "minute": 31
  },
  {
    "match_id": "16038",
    "season": 2014,
    "player_key": "橋本 拳人",
    "player_name": "橋本 拳人",
    "type": "警告",
    "time": "36'",
    "minute": 36
  },
  {
    "match_id": "16038",
    "season": 2014,
    "player_key": "岡本 賢明",
    "player_name": "岡本 賢明",
    "type": "警告",
    "time": "48'",
    "minute": 48
  },
  {
    "match_id": "16038",
    "season": 2014,
    "player_key": "齊藤 和樹",
    "player_name": "齊藤 和樹",
    "type": "警告",
    "time": "73'",
    "minute": 73
  },
  {
    "match_id": "16038",
    "season": 2014,
    "player_key": "橋本 拳人",
    "player_name": "橋本 拳人",
    "type": "警告",
    "time": "80'",
    "minute": 80
  },
  {
    "match_id": "16038",
    "season": 2014,
    "player_key": "橋本 拳人",
    "player_name": "橋本 拳人",
    "type": "退場",
    "time": "80'",
    "minute": 80
  },
  {
    "match_id": "16051",
    "season": 2014,
    "player_key": "養父 雄仁",
    "player_name": "養父 雄仁",
    "type": "警告",
    "time": "13'",
    "minute": 13
  },
  {
    "match_id": "16060",
    "season": 2014,
    "player_key": "園田 拓也",
    "player_name": "園田 拓也",
    "type": "警告",
    "time": "79'",
    "minute": 79
  },
  {
    "match_id": "16083",
    "season": 2014,
    "player_key": "養父 雄仁",
    "player_name": "養父 雄仁",
    "type": "警告",
    "time": "22'",
    "minute": 22
  },
  {
    "match_id": "16083",
    "season": 2014,
    "player_key": "仲間 隼斗",
    "player_name": "仲間 隼斗",
    "type": "警告",
    "time": "27'",
    "minute": 27
  },
  {
    "match_id": "16083",
    "season": 2014,
    "player_key": "藤本 主税",
    "player_name": "藤本 主税",
    "type": "警告",
    "time": "72'",
    "minute": 72
  },
  {
    "match_id": "16094",
    "season": 2014,
    "player_key": "原田 拓",
    "player_name": "原田 拓",
    "type": "警告",
    "time": "81'",
    "minute": 81
  },
  {
    "match_id": "16096",
    "season": 2014,
    "player_key": "片山 奨典",
    "player_name": "片山 奨典",
    "type": "警告",
    "time": "27'",
    "minute": 27
  },
  {
    "match_id": "16116",
    "season": 2014,
    "player_key": "中山 雄登",
    "player_name": "中山 雄登",
    "type": "警告",
    "time": "16'",
    "minute": 16
  },
  {
    "match_id": "16124",
    "season": 2014,
    "player_key": "養父 雄仁",
    "player_name": "養父 雄仁",
    "type": "警告",
    "time": "25'",
    "minute": 25
  },
  {
    "match_id": "16124",
    "season": 2014,
    "player_key": "澤田 崇",
    "player_name": "澤田 崇",
    "type": "警告",
    "time": "40'",
    "minute": 40
  },
  {
    "match_id": "16124",
    "season": 2014,
    "player_key": "中山 雄登",
    "player_name": "中山 雄登",
    "type": "警告",
    "time": "46'",
    "minute": 46
  },
  {
    "match_id": "16124",
    "season": 2014,
    "player_key": "片山 奨典",
    "player_name": "片山 奨典",
    "type": "警告",
    "time": "70'",
    "minute": 70
  },
  {
    "match_id": "16160",
    "season": 2014,
    "player_key": "養父 雄仁",
    "player_name": "養父 雄仁",
    "type": "警告",
    "time": "77'",
    "minute": 77
  },
  {
    "match_id": "16182",
    "season": 2014,
    "player_key": "片山 奨典",
    "player_name": "片山 奨典",
    "type": "警告",
    "time": "29'",
    "minute": 29
  },
  {
    "match_id": "16193",
    "season": 2014,
    "player_key": "中山 雄登",
    "player_name": "中山 雄登",
    "type": "警告",
    "time": "36'",
    "minute": 36
  },
  {
    "match_id": "16193",
    "season": 2014,
    "player_key": "橋本 拳人",
    "player_name": "橋本 拳人",
    "type": "警告",
    "time": "49'",
    "minute": 49
  },
  {
    "match_id": "16214",
    "season": 2014,
    "player_key": "片山 奨典",
    "player_name": "片山 奨典",
    "type": "警告",
    "time": "05'",
    "minute": 5
  },
  {
    "match_id": "16214",
    "season": 2014,
    "player_key": "仲間 隼斗",
    "player_name": "仲間 隼斗",
    "type": "警告",
    "time": "59'",
    "minute": 59
  },
  {
    "match_id": "16214",
    "season": 2014,
    "player_key": "橋本 拳人",
    "player_name": "橋本 拳人",
    "type": "警告",
    "time": "90'+1",
    "minute": 91
  },
  {
    "match_id": "16227",
    "season": 2014,
    "player_key": "黒木 晃平",
    "player_name": "黒木 晃平",
    "type": "警告",
    "time": "53'",
    "minute": 53
  },
  {
    "match_id": "16227",
    "season": 2014,
    "player_key": "片山 奨典",
    "player_name": "片山 奨典",
    "type": "警告",
    "time": "60'",
    "minute": 60
  },
  {
    "match_id": "16227",
    "season": 2014,
    "player_key": "巻 誠一郎",
    "player_name": "巻 誠一郎",
    "type": "警告",
    "time": "87'",
    "minute": 87
  },
  {
    "match_id": "16227",
    "season": 2014,
    "player_key": "片山 奨典",
    "player_name": "片山 奨典",
    "type": "警告",
    "time": "90'+1",
    "minute": 91
  },
  {
    "match_id": "16227",
    "season": 2014,
    "player_key": "片山 奨典",
    "player_name": "片山 奨典",
    "type": "退場",
    "time": "90'+1",
    "minute": 91
  },
  {
    "match_id": "16232",
    "season": 2014,
    "player_key": "養父 雄仁",
    "player_name": "養父 雄仁",
    "type": "警告",
    "time": "33'",
    "minute": 33
  },
  {
    "match_id": "16232",
    "season": 2014,
    "player_key": "園田 拓也",
    "player_name": "園田 拓也",
    "type": "警告",
    "time": "52'",
    "minute": 52
  },
  {
    "match_id": "16232",
    "season": 2014,
    "player_key": "藏川 洋平",
    "player_name": "藏川 洋平",
    "type": "警告",
    "time": "56'",
    "minute": 56
  },
  {
    "match_id": "16249",
    "season": 2014,
    "player_key": "上村 周平",
    "player_name": "上村 周平",
    "type": "警告",
    "time": "54'",
    "minute": 54
  },
  {
    "match_id": "16255",
    "season": 2014,
    "player_key": "橋本 拳人",
    "player_name": "橋本 拳人",
    "type": "警告",
    "time": "21'",
    "minute": 21
  },
  {
    "match_id": "16255",
    "season": 2014,
    "player_key": "藏川 洋平",
    "player_name": "藏川 洋平",
    "type": "警告",
    "time": "83'",
    "minute": 83
  },
  {
    "match_id": "16271",
    "season": 2014,
    "player_key": "仲間 隼斗",
    "player_name": "仲間 隼斗",
    "type": "警告",
    "time": "22'",
    "minute": 22
  },
  {
    "match_id": "16271",
    "season": 2014,
    "player_key": "髙柳 一誠",
    "player_name": "髙柳 一誠",
    "type": "警告",
    "time": "81'",
    "minute": 81
  },
  {
    "match_id": "16271",
    "season": 2014,
    "player_key": "篠原 弘次郎",
    "player_name": "篠原 弘次郎",
    "type": "警告",
    "time": "87'",
    "minute": 87
  },
  {
    "match_id": "16275",
    "season": 2014,
    "player_key": "澤田 崇",
    "player_name": "澤田 崇",
    "type": "警告",
    "time": "38'",
    "minute": 38
  },
  {
    "match_id": "16275",
    "season": 2014,
    "player_key": "齊藤 和樹",
    "player_name": "齊藤 和樹",
    "type": "警告",
    "time": "80'",
    "minute": 80
  },
  {
    "match_id": "16292",
    "season": 2014,
    "player_key": "養父 雄仁",
    "player_name": "養父 雄仁",
    "type": "警告",
    "time": "83'",
    "minute": 83
  },
  {
    "match_id": "16292",
    "season": 2014,
    "player_key": "藏川 洋平",
    "player_name": "藏川 洋平",
    "type": "警告",
    "time": "90'+5",
    "minute": 95
  },
  {
    "match_id": "16315",
    "season": 2014,
    "player_key": "仲間 隼斗",
    "player_name": "仲間 隼斗",
    "type": "警告",
    "time": "45'+2",
    "minute": 47
  },
  {
    "match_id": "16315",
    "season": 2014,
    "player_key": "齊藤 和樹",
    "player_name": "齊藤 和樹",
    "type": "警告",
    "time": "83'",
    "minute": 83
  },
  {
    "match_id": "16315",
    "season": 2014,
    "player_key": "アンデルソン",
    "player_name": "アンデルソン",
    "type": "警告",
    "time": "90'",
    "minute": 90
  },
  {
    "match_id": "16315",
    "season": 2014,
    "player_key": "アンデルソン",
    "player_name": "アンデルソン",
    "type": "警告",
    "time": "90'+1",
    "minute": 91
  },
  {
    "match_id": "16315",
    "season": 2014,
    "player_key": "アンデルソン",
    "player_name": "アンデルソン",
    "type": "退場",
    "time": "90'+1",
    "minute": 91
  },
  {
    "match_id": "16325",
    "season": 2014,
    "player_key": "片山 奨典",
    "player_name": "片山 奨典",
    "type": "警告",
    "time": "55'",
    "minute": 55
  },
  {
    "match_id": "16332",
    "season": 2014,
    "player_key": "橋本 拳人",
    "player_name": "橋本 拳人",
    "type": "警告",
    "time": "04'",
    "minute": 4
  },
  {
    "match_id": "16332",
    "season": 2014,
    "player_key": "仲間 隼斗",
    "player_name": "仲間 隼斗",
    "type": "警告",
    "time": "27'",
    "minute": 27
  },
  {
    "match_id": "16352",
    "season": 2014,
    "player_key": "仲間 隼斗",
    "player_name": "仲間 隼斗",
    "type": "警告",
    "time": "29'",
    "minute": 29
  },
  {
    "match_id": "16368",
    "season": 2014,
    "player_key": "キム ビョンヨン",
    "player_name": "キム ビョンヨン",
    "type": "警告",
    "time": "08'",
    "minute": 8
  },
  {
    "match_id": "16368",
    "season": 2014,
    "player_key": "髙柳 一誠",
    "player_name": "髙柳 一誠",
    "type": "警告",
    "time": "76'",
    "minute": 76
  },
  {
    "match_id": "16379",
    "season": 2014,
    "player_key": "黒木 晃平",
    "player_name": "黒木 晃平",
    "type": "警告",
    "time": "90'+2",
    "minute": 92
  },
  {
    "match_id": "16391",
    "season": 2014,
    "player_key": "篠原 弘次郎",
    "player_name": "篠原 弘次郎",
    "type": "警告",
    "time": "30'",
    "minute": 30
  },
  {
    "match_id": "16391",
    "season": 2014,
    "player_key": "キム ビョンヨン",
    "player_name": "キム ビョンヨン",
    "type": "警告",
    "time": "41'",
    "minute": 41
  },
  {
    "match_id": "16403",
    "season": 2014,
    "player_key": "篠原 弘次郎",
    "player_name": "篠原 弘次郎",
    "type": "警告",
    "time": "40'",
    "minute": 40
  },
  {
    "match_id": "16403",
    "season": 2014,
    "player_key": "髙柳 一誠",
    "player_name": "髙柳 一誠",
    "type": "警告",
    "time": "61'",
    "minute": 61
  },
  {
    "match_id": "16413",
    "season": 2014,
    "player_key": "藏川 洋平",
    "player_name": "藏川 洋平",
    "type": "警告",
    "time": "36'",
    "minute": 36
  },
  {
    "match_id": "16413",
    "season": 2014,
    "player_key": "中山 雄登",
    "player_name": "中山 雄登",
    "type": "警告",
    "time": "37'",
    "minute": 37
  },
  {
    "match_id": "16413",
    "season": 2014,
    "player_key": "藤本 主税",
    "player_name": "藤本 主税",
    "type": "警告",
    "time": "88'",
    "minute": 88
  },
  {
    "match_id": "16435",
    "season": 2014,
    "player_key": "嶋田 慎太郎",
    "player_name": "嶋田 慎太郎",
    "type": "警告",
    "time": "08'",
    "minute": 8
  },
  {
    "match_id": "16435",
    "season": 2014,
    "player_key": "齊藤 和樹",
    "player_name": "齊藤 和樹",
    "type": "警告",
    "time": "60'",
    "minute": 60
  }
]