[
  {
    "player_key": "ホージェル ガウーショ",
    "player_name": "ホージェル ガウーショ"
  },
  {
    "player_key": "ラファエル シルバ",
    "player_name": "ラファエル シルバ"
  },
  {
    "player_key": "レオ シルバ",
    "player_name": "レオ シルバ"
  },
  {
    "player_key": "加藤 大",
    "player_name": "加藤 大"
  },
  {
    "player_key": "坪内 秀介",
    "player_name": "坪内 秀介"
  },
  {
    "player_key": "大井 健太郎",
    "player_name": "大井 健太郎"
  },
  {
    "player_key": "大野 和成",
    "player_name": "大野 和成"
  },
  {
    "player_key": "守田 達弥",
    "player_name": "守田 達弥"
  },
  {
    "player_key": "宋 株熏",
    "player_name": "宋 株熏"
  },
  {
    "player_key": "小塚 和季",
    "player_name": "小塚 和季"
  },
  {
    "player_key": "小林 裕紀",
    "player_name": "小林 裕紀"
  },
  {
    "player_key": "小泉 慶",
    "player_name": "小泉 慶"
  },
  {
    "player_key": "山本 康裕",
    "player_name": "山本 康裕"
  },
  {
    "player_key": "岡本 英也",
    "player_name": "岡本 英也"
  },
  {
    "player_key": "川又 堅碁",
    "player_name": "川又 堅碁"
  },
  {
    "player_key": "川口 尚紀",
    "player_name": "川口 尚紀"
  },
  {
    "player_key": "成岡 翔",
    "player_name": "成岡 翔"
  },
  {
    "player_key": "指宿 洋史",
    "player_name": "指宿 洋史"
  },
  {
    "player_key": "本間 勲",
    "player_name": "本間 勲"
  },
  {
    "player_key": "李 明載",
    "player_name": "李 明載"
  },
  {
    "player_key": "松原 健",
    "player_name": "松原 健"
  },
  {
    "player_key": "渡辺 泰広",
    "player_name": "渡辺 泰広"
  },
  {
    "player_key": "田中 亜土夢",
    "player_name": "田中 亜土夢"
  },
  {
    "player_key": "田中 達也",
    "player_name": "田中 達也"
  },
  {
    "player_key": "舞行龍ジェームズ",
    "player_name": "舞行龍ジェームズ"
  },
  {
    "player_key": "酒井 高聖",
    "player_name": "酒井 高聖"
  },
  {
    "player_key": "金 珍洙",
    "player_name": "金 珍洙"
  },
  {
    "player_key": "鈴木 武蔵",
    "player_name": "鈴木 武蔵"
  },
  {
    "player_key": "黒河 貴矢",
    "player_name": "黒河 貴矢"
  }
]