[
  {
    "player_key": "クォン ソックン",
    "player_name": "クォン ソックン"
  },
  {
    "player_key": "上村 健一",
    "player_name": "上村 健一"
  },
  {
    "player_key": "中山 悟志",
    "player_name": "中山 悟志"
  },
  {
    "player_key": "北川 佳男",
    "player_name": "北川 佳男"
  },
  {
    "player_key": "吉井 孝輔",
    "player_name": "吉井 孝輔"
  },
  {
    "player_key": "吉田 智志",
    "player_name": "吉田 智志"
  },
  {
    "player_key": "喜名 哲裕",
    "player_name": "喜名 哲裕"
  },
  {
    "player_key": "太 洋一",
    "player_name": "太 洋一"
  },
  {
    "player_key": "宮崎 大志郎",
    "player_name": "宮崎 大志郎"
  },
  {
    "player_key": "小林 弘記",
    "player_name": "小林 弘記"
  },
  {
    "player_key": "小林 陽介",
    "player_name": "小林 陽介"
  },
  {
    "player_key": "小森田 友明",
    "player_name": "小森田 友明"
  },
  {
    "player_key": "山内 祐一",
    "player_name": "山内 祐一"
  },
  {
    "player_key": "山口 武士",
    "player_name": "山口 武士"
  },
  {
    "player_key": "山本 翔平",
    "player_name": "山本 翔平"
  },
  {
    "player_key": "市村 篤司",
    "player_name": "市村 篤司"
  },
  {
    "player_key": "斉藤 紀由",
    "player_name": "斉藤 紀由"
  },
  {
    "player_key": "有村 光史",
    "player_name": "有村 光史"
  },
  {
    "player_key": "木島 良輔",
    "player_name": "木島 良輔"
  },
  {
    "player_key": "松岡 康暢",
    "player_name": "松岡 康暢"
  },
  {
    "player_key": "河端 和哉",
    "player_name": "河端 和哉"
  },
  {
    "player_key": "河野 健一",
    "player_name": "河野 健一"
  },
  {
    "player_key": "熊谷 雅彦",
    "player_name": "熊谷 雅彦"
  },
  {
    "player_key": "町田 多聞",
    "player_name": "町田 多聞"
  },
  {
    "player_key": "矢野 大輔",
    "player_name": "矢野 大輔"
  },
  {
    "player_key": "福王 忠世",
    "player_name": "福王 忠世"
  },
  {
    "player_key": "稲田 康志",
    "player_name": "稲田 康志"
  },
  {
    "player_key": "西森 正明",
    "player_name": "西森 正明"
  },
  {
    "player_key": "車 智鎬",
    "player_name": "車 智鎬"
  },
  {
    "player_key": "鈴木 祐輔",
    "player_name": "鈴木 祐輔"
  },
  {
    "player_key": "関 光博",
    "player_name": "関 光博"
  },
  {
    "player_key": "高橋 泰",
    "player_name": "高橋 泰"
  }
]