[
  {
    "match_id": "9987",
    "season": 2007,
    "player_key": "矢野 貴章",
    "player_name": "矢野 貴章",
    "time": "53'",
    "minute": 53,
    "is_own_goal": false
  },
  {
    "match_id": "10001",
    "season": 2007,
    "player_key": "河原 和寿",
    "player_name": "河原 和寿",
    "time": "88'",
    "minute": 88,
    "is_own_goal": false
  },
  {
    "match_id": "10001",
    "season": 2007,
    "player_key": "田中 亜土夢",
    "player_name": "田中 亜土夢",
    "time": "89'",
    "minute": 89,
    "is_own_goal": false
  },
  {
    "match_id": "9954",
    "season": 2007,
    "player_key": "マルシオ リシャルデス",
    "player_name": "マルシオ リシャルデス",
    "time": "03'",
    "minute": 3,
    "is_own_goal": false
  },
  {
    "match_id": "9954",
    "season": 2007,
    "player_key": "エジミウソン",
    "player_name": "エジミウソン",
    "time": "68'",
    "minute": 68,
    "is_own_goal": false
  },
  {
    "match_id": "9954",
    "season": 2007,
    "player_key": "矢野 貴章",
    "player_name": "矢野 貴章",
    "time": "87'",
    "minute": 87,
    "is_own_goal": false
  },
  {
    "match_id": "9955",
    "season": 2007,
    "player_key": "エジミウソン",
    "player_name": "エジミウソン",
    "time": "47'",
    "minute": 47,
    "is_own_goal": false
  },
  {
    "match_id": "10013",
    "season": 2007,
    "player_key": "矢野 貴章",
    "player_name": "矢野 貴章",
    "time": "73'",
    "minute": 73,
    "is_own_goal": false
  },
  {
    "match_id": "10013",
    "season": 2007,
    "player_key": "エジミウソン",
    "player_name": "エジミウソン",
    "time": "87'",
    "minute": 87,
    "is_own_goal": false
  },
  {
    "match_id": "9958",
    "season": 2007,
    "player_key": "エジミウソン",
    "player_name": "エジミウソン",
    "time": "71'",
    "minute": 71,
    "is_own_goal": false
  },
  {
    "match_id": "9958",
    "season": 2007,
    "player_key": "深井 正樹",
    "player_name": "深井 正樹",
    "time": "84'",
    "minute": 84,
    "is_own_goal": false
  },
  {
    "match_id": "10022",
    "season": 2007,
    "player_key": "坂本 將貴",
    "player_name": "坂本 將貴",
    "time": "21'",
    "minute": 21,
    "is_own_goal": false
  },
  {
    "match_id": "10022",
    "season": 2007,
    "player_key": "マルシオ リシャルデス",
    "player_name": "マルシオ リシャルデス",
    "time": "52'",
    "minute": 52,
    "is_own_goal": false
  },
  {
    "match_id": "10022",
    "season": 2007,
    "player_key": "エジミウソン",
    "player_name": "エジミウソン",
    "time": "55'",
    "minute": 55,
    "is_own_goal": false
  },
  {
    "match_id": "9960",
    "season": 2007,
    "player_key": "マルシオ リシャルデス",
    "player_name": "マルシオ リシャルデス",
    "time": "01'",
    "minute": 1,
    "is_own_goal": false
  },
  {
    "match_id": "9960",
    "season": 2007,
    "player_key": "千葉 和彦",
    "player_name": "千葉 和彦",
    "time": "55'",
    "minute": 55,
    "is_own_goal": false
  },
  {
    "match_id": "10033",
    "season": 2007,
    "player_key": "シルビーニョ",
    "player_name": "シルビーニョ",
    "time": "44'",
    "minute": 44,
    "is_own_goal": false
  },
  {
    "match_id": "10033",
    "season": 2007,
    "player_key": "矢野 貴章",
    "player_name": "矢野 貴章",
    "time": "82'",
    "minute": 82,
    "is_own_goal": false
  },
  {
    "match_id": "10068",
    "season": 2007,
    "player_key": "エジミウソン",
    "player_name": "エジミウソン",
    "time": "58'",
    "minute": 58,
    "is_own_goal": false
  },
  {
    "match_id": "10068",
    "season": 2007,
    "player_key": "エジミウソン",
    "player_name": "エジミウソン",
    "time": "76'",
    "minute": 76,
    "is_own_goal": false
  },
  {
    "match_id": "10068",
    "season": 2007,
    "player_key": "深井 正樹",
    "player_name": "深井 正樹",
    "time": "89'",
    "minute": 89,
    "is_own_goal": false
  },
  {
    "match_id": "10077",
    "season": 2007,
    "player_key": "エジミウソン",
    "player_name": "エジミウソン",
    "time": "88'",
    "minute": 88,
    "is_own_goal": false
  },
  {
    "match_id": "10101",
    "season": 2007,
    "player_key": "エジミウソン",
    "player_name": "エジミウソン",
    "time": "03'",
    "minute": 3,
    "is_own_goal": false
  },
  {
    "match_id": "10101",
    "season": 2007,
    "player_key": "矢野 貴章",
    "player_name": "矢野 貴章",
    "time": "52'",
    "minute": 52,
    "is_own_goal": false
  },
  {
    "match_id": "10101",
    "season": 2007,
    "player_key": "マルシオ リシャルデス",
    "player_name": "マルシオ リシャルデス",
    "time": "73'",
    "minute": 73,
    "is_own_goal": false
  },
  {
    "match_id": "10101",
    "season": 2007,
    "player_key": "エジミウソン",
    "player_name": "エジミウソン",
    "time": "80'",
    "minute": 80,
    "is_own_goal": false
  },
  {
    "match_id": "10104",
    "season": 2007,
    "player_key": "マルシオ リシャルデス",
    "player_name": "マルシオ リシャルデス",
    "time": "36'",
    "minute": 36,
    "is_own_goal": false
  },
  {
    "match_id": "10104",
    "season": 2007,
    "player_key": "マルシオ リシャルデス",
    "player_name": "マルシオ リシャルデス",
    "time": "53'",
    "minute": 53,
    "is_own_goal": false
  },
  {
    "match_id": "10104",
    "season": 2007,
    "player_key": "エジミウソン",
    "player_name": "エジミウソン",
    "time": "67'",
    "minute": 67,
    "is_own_goal": false
  },
  {
    "match_id": "10116",
    "season": 2007,
    "player_key": "千代反田 充",
    "player_name": "千代反田 充",
    "time": "72'",
    "minute": 72,
    "is_own_goal": false
  },
  {
    "match_id": "10124",
    "season": 2007,
    "player_key": "内田 潤",
    "player_name": "内田 潤",
    "time": "14'",
    "minute": 14,
    "is_own_goal": false
  },
  {
    "match_id": "10124",
    "season": 2007,
    "player_key": "エジミウソン",
    "player_name": "エジミウソン",
    "time": "27'",
    "minute": 27,
    "is_own_goal": false
  },
  {
    "match_id": "10124",
    "season": 2007,
    "player_key": "エジミウソン",
    "player_name": "エジミウソン",
    "time": "41'",
    "minute": 41,
    "is_own_goal": false
  },
  {
    "match_id": "10131",
    "season": 2007,
    "player_key": "矢野 貴章",
    "player_name": "矢野 貴章",
    "time": "49'",
    "minute": 49,
    "is_own_goal": false
  },
  {
    "match_id": "10131",
    "season": 2007,
    "player_key": "内田 潤",
    "player_name": "内田 潤",
    "time": "80'",
    "minute": 80,
    "is_own_goal": false
  },
  {
    "match_id": "10152",
    "season": 2007,
    "player_key": "マルシオ リシャルデス",
    "player_name": "マルシオ リシャルデス",
    "time": "87'",
    "minute": 87,
    "is_own_goal": false
  },
  {
    "match_id": "10161",
    "season": 2007,
    "player_key": "本間 勲",
    "player_name": "本間 勲",
    "time": "11'",
    "minute": 11,
    "is_own_goal": false
  },
  {
    "match_id": "10161",
    "season": 2007,
    "player_key": "矢野 貴章",
    "player_name": "矢野 貴章",
    "time": "34'",
    "minute": 34,
    "is_own_goal": false
  },
  {
    "match_id": "10161",
    "season": 2007,
    "player_key": "エジミウソン",
    "player_name": "エジミウソン",
    "time": "48'",
    "minute": 48,
    "is_own_goal": false
  },
  {
    "match_id": "10161",
    "season": 2007,
    "player_key": "エジミウソン",
    "player_name": "エジミウソン",
    "time": "79'",
    "minute": 79,
    "is_own_goal": false
  },
  {
    "match_id": "10187",
    "season": 2007,
    "player_key": "坂本 將貴",
    "player_name": "坂本 將貴",
    "time": "25'",
    "minute": 25,
    "is_own_goal": false
  },
  {
    "match_id": "10208",
    "season": 2007,
    "player_key": "本間 勲",
    "player_name": "本間 勲",
    "time": "02'",
    "minute": 2,
    "is_own_goal": false
  },
  {
    "match_id": "10210",
    "season": 2007,
    "player_key": "矢野 貴章",
    "player_name": "矢野 貴章",
    "time": "03'",
    "minute": 3,
    "is_own_goal": false
  },
  {
    "match_id": "10232",
    "season": 2007,
    "player_key": "エジミウソン",
    "player_name": "エジミウソン",
    "time": "89'",
    "minute": 89,
    "is_own_goal": false
  },
  {
    "match_id": "10239",
    "season": 2007,
    "player_key": "エジミウソン",
    "player_name": "エジミウソン",
    "time": "25'",
    "minute": 25,
    "is_own_goal": false
  },
  {
    "match_id": "10239",
    "season": 2007,
    "player_key": "千代反田 充",
    "player_name": "千代反田 充",
    "time": "56'",
    "minute": 56,
    "is_own_goal": false
  },
  {
    "match_id": "10239",
    "season": 2007,
    "player_key": "マルシオ リシャルデス",
    "player_name": "マルシオ リシャルデス",
    "time": "65'",
    "minute": 65,
    "is_own_goal": false
  },
  {
    "match_id": "10250",
    "season": 2007,
    "player_key": "エジミウソン",
    "player_name": "エジミウソン",
    "time": "37'",
    "minute": 37,
    "is_own_goal": false
  },
  {
    "match_id": "10257",
    "season": 2007,
    "player_key": "エジミウソン",
    "player_name": "エジミウソン",
    "time": "60'",
    "minute": 60,
    "is_own_goal": false
  },
  {
    "match_id": "10257",
    "season": 2007,
    "player_key": "エジミウソン",
    "player_name": "エジミウソン",
    "time": "83'",
    "minute": 83,
    "is_own_goal": false
  },
  {
    "match_id": "10268",
    "season": 2007,
    "player_key": "エジミウソン",
    "player_name": "エジミウソン",
    "time": "85'",
    "minute": 85,
    "is_own_goal": false
  },
  {
    "match_id": "10268",
    "season": 2007,
    "player_key": "エジミウソン",
    "player_name": "エジミウソン",
    "time": "89'",
    "minute": 89,
    "is_own_goal": false
  }
]