{
  "batchcomplete": "",
  "query": {
    "searchinfo": {
      "totalhits": 4
    },
    "search": [
      {
        "ns": 0,
        "title": "List of J2 League football transfers winter 2019–20",
        "pageid": 62925473,
        "size": 86050,
        "wordcount": 693,
        "snippet": "選手期限付き移籍加入内定のお知らせ&quot;. アルビレックス新潟 公式サイト｜<span class=\"searchmatch\">ALBIREX</span> <span class=\"searchmatch\">NIIGATA</span> OFFICIAL WEBSITE. &quot;ブラジル・オエスチFCからファビオ選手 移籍加入内定のお知らせ&quot;. アルビレックス新潟 公式サイト｜<span class=\"searchmatch\">ALBIREX</span> <span class=\"searchmatch\">NIIGATA</span> OFFICIAL WEBSITE. &quot;インド・チェンナイ",
        "timestamp": "2026-05-08T15:36:12Z"
      },
      {
        "ns": 0,
        "title": "List of J2 League football transfers winter 2023–24",
        "pageid": 76217127,
        "size": 247552,
        "wordcount": 13714,
        "snippet": "公式サイト｜<span class=\"searchmatch\">ALBIREX</span> <span class=\"searchmatch\">NIIGATA</span> OFFICIAL WEBSITE (in Japanese). 13 December 2023. Retrieved 22 December 2023. &quot;遠藤 凌 選手 期限付き移籍より復帰のお知らせ&quot;. アルビレックス新潟 公式サイト｜<span class=\"searchmatch\">ALBIREX</span> NIIGATA",
        "timestamp": "2026-05-08T15:43:15Z"
      },
      {
        "ns": 0,
        "title": "List of Japanese football transfers winter 2009–10",
        "pageid": 25358362,
        "size": 62412,
        "wordcount": 2067,
        "snippet": "2009-12-01. Archived from the original on 2009-12-04. Retrieved 2009-12-11. フラビオ・<span class=\"searchmatch\">アウグスト</span>・ペレイラ選手、新加入内定のお知らせ (in Japanese). fc-gifu.com. 2009-12-01. Archived from",
        "timestamp": "2026-05-09T00:51:32Z"
      },
      {
        "ns": 0,
        "title": "2019 J1 League",
        "pageid": 59406002,
        "size": 58598,
        "wordcount": 1911,
        "snippet": "公式WEBサイト. &quot;エウシーニョ選手(川崎フロンターレ) 完全移籍にて加入決定のお知らせ&quot;. 清水エスパルス 公式WEBサイト. &quot;ヘナト <span class=\"searchmatch\">アウグスト</span>選手(SEパルメイラス/ブラジル) 完全移籍にて加入決定のお知らせ&quot;. 清水エスパルス 公式WEBサイト. &quot;契約更新選手のお知らせ&quot;. 清水エスパルス",
        "timestamp": "2025-12-30T09:26:12Z"
      }
    ]
  }
}
